specparam/__init__.py
specparam/version.py
specparam/algorithms/__init__.py
specparam/algorithms/algorithm.py
specparam/algorithms/definitions.py
specparam/algorithms/settings.py
specparam/algorithms/spectral_fit.py
specparam/bands/__init__.py
specparam/bands/bands.py
specparam/convert/__init__.py
specparam/convert/convert.py
specparam/convert/converter.py
specparam/convert/definitions.py
specparam/convert/params.py
specparam/data/__init__.py
specparam/data/conversions.py
specparam/data/data.py
specparam/data/periodic.py
specparam/data/stores.py
specparam/data/utils.py
specparam/io/__init__.py
specparam/io/files.py
specparam/io/models.py
specparam/io/utils.py
specparam/measures/__init__.py
specparam/measures/estimates.py
specparam/measures/params.py
specparam/measures/pointwise.py
specparam/measures/properties.py
specparam/metrics/__init__.py
specparam/metrics/definitions.py
specparam/metrics/error.py
specparam/metrics/gof.py
specparam/metrics/metric.py
specparam/metrics/metrics.py
specparam/models/__init__.py
specparam/models/base.py
specparam/models/event.py
specparam/models/group.py
specparam/models/model.py
specparam/models/time.py
specparam/models/utils.py
specparam/modes/__init__.py
specparam/modes/definitions.py
specparam/modes/funcs.py
specparam/modes/jacobians.py
specparam/modes/mode.py
specparam/modes/modes.py
specparam/modes/params.py
specparam/modutils/__init__.py
specparam/modutils/dependencies.py
specparam/modutils/docs.py
specparam/modutils/errors.py
specparam/modutils/functions.py
specparam/plts/__init__.py
specparam/plts/annotate.py
specparam/plts/aperiodic.py
specparam/plts/error.py
specparam/plts/event.py
specparam/plts/group.py
specparam/plts/model.py
specparam/plts/periodic.py
specparam/plts/settings.py
specparam/plts/spectra.py
specparam/plts/style.py
specparam/plts/templates.py
specparam/plts/time.py
specparam/plts/utils.py
specparam/reports/__init__.py
specparam/reports/methods.py
specparam/reports/save.py
specparam/reports/settings.py
specparam-2.0.0rc6.dist-info/LICENSE
specparam-2.0.0rc6.dist-info/METADATA
specparam-2.0.0rc6.dist-info/WHEEL
specparam-2.0.0rc6.dist-info/top_level.txt
specparam-2.0.0rc6.dist-info/RECORD
